Metadata-Version: 2.1
Name: my-find-files
Version: 1.0.0
Summary: 遍历一个路径
Author: zhuquan
Author-email: 2661194101@qq.com
